.travis.yml
AUTHORS
ChangeLog
README.rst
VERSION
release.sh
requirements.txt
setup.cfg
setup.py
test-requirements.txt
tox.ini
tests/__init__.py
tests/simple_app.py
tests/test_simpleroute.py
tomb_routes/__init__.py
tomb_routes.egg-info/PKG-INFO
tomb_routes.egg-info/SOURCES.txt
tomb_routes.egg-info/dependency_links.txt
tomb_routes.egg-info/not-zip-safe
tomb_routes.egg-info/pbr.json
tomb_routes.egg-info/requires.txt
tomb_routes.egg-info/top_level.txt