Metadata-Version: 1.0
Name: tomb-routes
Version: 0.0.6
Summary: A set of sane routing defaults for the Pyramid web framework
Home-page: https://github.com/tomborine/tomb_routes
Author: John Anderson, Marc Abramowitz
Author-email: johna@gmail.com
License: MIT
Platform: UNKNOWN
